keygen_licensing_tools.cpython-39-x86_64-linux-gnu.so
keygen_licensing_tools.pyi
keygen_licensing_tools/_main.pyi
keygen_licensing_tools/_exceptions.pyi
keygen_licensing_tools/__about__.pyi
keygen_licensing_tools/py.typed
keygen_licensing_tools/_helpers.pyi
keygen_licensing_tools/_offline_keys.pyi
keygen_licensing_tools/__init__.pyi
keygen_licensing_tools-0.3.1.dist-info/LICENSE
keygen_licensing_tools-0.3.1.dist-info/METADATA
keygen_licensing_tools-0.3.1.dist-info/top_level.txt
keygen_licensing_tools-0.3.1.dist-info/RECORD
keygen_licensing_tools-0.3.1.dist-info/WHEEL
