Metadata-Version: 2.1
Name: keygen-licensing-tools
Version: 0.3.1
Summary: Python tools for Keygen.sh licensing
Author: Nico Schlömer
Author-email: nico.schloemer@gmail.com
License: UNKNOWN
Platform: UNKNOWN
Classifier: Development Status :: 4 - Beta
Classifier: License :: Other/Proprietary License
Classifier: Operating System :: OS Independent
Classifier: Programming Language :: Python
Classifier: Programming Language :: Python :: 3
Classifier: Programming Language :: Python :: 3.7
Classifier: Programming Language :: Python :: 3.8
Classifier: Programming Language :: Python :: 3.9
Classifier: Programming Language :: Python :: 3.10
Classifier: Topic :: Utilities
Requires-Python: >=3.7
License-File: LICENSE
Requires-Dist: appdirs
Requires-Dist: cryptography
Requires-Dist: requests
Requires-Dist: ed25519
Requires-Dist: rich
Requires-Dist: tomli
Requires-Dist: tomli-w
Requires-Dist: importlib-metadata ; python_version < "3.8"
